git_joke_cli-1.1.2.data/scripts/git-joke
gitjoke/__init__.py
gitjoke/extractor.py
git_joke_cli-1.1.2.dist-info/METADATA
git_joke_cli-1.1.2.dist-info/WHEEL
git_joke_cli-1.1.2.dist-info/top_level.txt
git_joke_cli-1.1.2.dist-info/RECORD
