Metadata-Version: 2.1
Name: git-joke-cli
Version: 1.1.2
Summary: Get git joke in command line
Home-page: https://github.com/vitakrya/git-joke-cli
Author: Vita Kr
License: MIT
Platform: UNKNOWN
Requires-Dist: requests
Requires-Dist: docopt
Requires-Dist: halo
